setup.py
src/Hatak_Auth.egg-info/PKG-INFO
src/Hatak_Auth.egg-info/SOURCES.txt
src/Hatak_Auth.egg-info/dependency_links.txt
src/Hatak_Auth.egg-info/namespace_packages.txt
src/Hatak_Auth.egg-info/not-zip-safe
src/Hatak_Auth.egg-info/requires.txt
src/Hatak_Auth.egg-info/top_level.txt
src/haplugin/__init__.py
src/haplugin/auth/__init__.py
src/haplugin/auth/controllers.py
src/haplugin/auth/db_tables.py
src/haplugin/auth/driver.py
src/haplugin/auth/forms.py
src/haplugin/auth/helpers.py
src/haplugin/auth/models.py
src/haplugin/auth/plugin.py
src/haplugin/auth/tests/__init__.py
src/haplugin/auth/tests/test_models.py
src/haplugin/auth/tests/test_plugin.py