Metadata-Version: 1.0
Name: Hatak-Auth
Version: 0.2.2.2
Summary: Auth plugin for Hatak.
Home-page: UNKNOWN
Author: UNKNOWN
Author-email: UNKNOWN
License: Apache License 2.0
Platform: UNKNOWN
